edc_protocol_violation/__init__.py
edc_protocol_violation/action_items.py
edc_protocol_violation/admin_site.py
edc_protocol_violation/apps.py
edc_protocol_violation/auth_objects.py
edc_protocol_violation/auths.py
edc_protocol_violation/choices.py
edc_protocol_violation/constants.py
edc_protocol_violation/list_data.py
edc_protocol_violation/urls.py
edc_protocol_violation/admin/__init__.py
edc_protocol_violation/admin/protocol_deviation_violation_admin.py
edc_protocol_violation/admin/protocol_incident_admin.py
edc_protocol_violation/form_validators/__init__.py
edc_protocol_violation/form_validators/mixins.py
edc_protocol_violation/form_validators/protocol_deviation_violation_form_validator.py
edc_protocol_violation/form_validators/protocol_incident_form_validator.py
edc_protocol_violation/forms/__init__.py
edc_protocol_violation/forms/protocol_deviation_violation_form.py
edc_protocol_violation/forms/protocol_incident_form.py
edc_protocol_violation/migrations/0001_initial.py
edc_protocol_violation/migrations/0002_auto_20210911_2036.py
edc_protocol_violation/migrations/0003_auto_20211104_1456.py
edc_protocol_violation/migrations/0004_alter_protocoldeviationviolation_violation.py
edc_protocol_violation/migrations/0005_protocolincident_historicalprotocolincident_and_more.py
edc_protocol_violation/migrations/0006_protocolincidents_and_more.py
edc_protocol_violation/migrations/0007_auto_20220704_1841.py
edc_protocol_violation/migrations/0008_alter_historicalprotocoldeviationviolation_action_identifier_and_more.py
edc_protocol_violation/migrations/0009_auto_20220826_0258.py
edc_protocol_violation/migrations/0010_auto_20220826_0322.py
edc_protocol_violation/migrations/0011_auto_20220826_0406.py
edc_protocol_violation/migrations/0012_auto_20220913_2139.py
edc_protocol_violation/migrations/__init__.py
edc_protocol_violation/model_mixins/__init__.py
edc_protocol_violation/model_mixins/protocol_deviation_violation_model_mixin.py
edc_protocol_violation-0.1.17.dist-info/AUTHORS
edc_protocol_violation-0.1.17.dist-info/LICENSE
edc_protocol_violation-0.1.17.dist-info/METADATA
edc_protocol_violation-0.1.17.dist-info/WHEEL
edc_protocol_violation-0.1.17.dist-info/top_level.txt
edc_protocol_violation-0.1.17.dist-info/RECORD
